{
    "__comment": "Model generated using MrCrayfish's Model Creator (http://mrcrayfish.com/modelcreator/)",
    "textures": {
        "0": "naturesgift:items/magical_nature_stick/stickpart",
        "1": "naturesgift:items/magical_nature_stick/bonetop"
    },
    "elements": [
        {
            "name": "Base",
            "from": [ 5.199999958276749, 0.2999999597668648, 7.0 ], 
            "to": [ 7.199999958276749, 8.299999959766865, 9.0 ], 
            "faces": {
                "north": { "texture": "#0", "uv": [ 5.0, 6.0, 7.0, 14.0 ] },
                "east": { "texture": "#0", "uv": [ 8.0, 6.0, 10.0, 14.0 ] },
                "south": { "texture": "#0", "uv": [ 2.0, 5.0, 4.0, 13.0 ] },
                "west": { "texture": "#0", "uv": [ 5.0, 5.0, 7.0, 13.0 ] },
                "up": { "texture": "#0", "uv": [ 9.0, 10.0, 11.0, 12.0 ] },
                "down": { "texture": "#0", "uv": [ 2.0, 9.0, 6.0, 12.0 ] }
            }
        },
        {
            "name": "boneBase",
            "from": [ 6.0, 8.0, 7.200000002980232 ], 
            "to": [ 7.0, 9.0, 8.600000008940697 ], 
            "faces": {
                "north": { "texture": "#1", "uv": [ 0.0, 0.0, 1.0, 1.0 ] },
                "east": { "texture": "#1", "uv": [ 0.0, 0.0, 1.4000000059604645, 1.0 ] },
                "south": { "texture": "#1", "uv": [ 0.0, 0.0, 1.0, 1.0 ] },
                "west": { "texture": "#1", "uv": [ 0.0, 0.0, 1.4000000059604645, 1.0 ] },
                "up": { "texture": "#1", "uv": [ 0.0, 0.0, 1.0, 1.4000000059604645 ] },
                "down": { "texture": "#1", "uv": [ 0.0, 0.0, 1.0, 1.4000000059604645 ] }
            }
        },
        {
            "name": "BoneBase2",
            "from": [ 5.0, 9.0, 7.200000002980232 ], 
            "to": [ 6.0, 10.0, 8.600000008940697 ], 
            "faces": {
                "north": { "texture": "#1", "uv": [ 0.0, 0.0, 1.0, 1.0 ] },
                "east": { "texture": "#1", "uv": [ 0.0, 0.0, 1.4000000059604645, 1.0 ] },
                "south": { "texture": "#1", "uv": [ 0.0, 0.0, 1.0, 1.0 ] },
                "west": { "texture": "#1", "uv": [ 0.0, 0.0, 1.4000000059604645, 1.0 ] },
                "up": { "texture": "#1", "uv": [ 0.0, 0.0, 1.0, 1.4000000059604645 ] },
                "down": { "texture": "#1", "uv": [ 0.0, 0.0, 1.0, 1.4000000059604645 ] }
            }
        },
        {
            "name": "bone rod",
            "from": [ 5.899999998509884, 8.699999995529652, 7.4000000059604645 ], 
            "to": [ 7.300000004470348, 15.80000002682209, 8.400000005960464 ], 
            "rotation": { "origin": [ 6.599999979138374, 9.599999994039536, 7.800000011920929 ], "axis": "z", "angle": -45.0 },
            "faces": {
                "north": { "texture": "#1", "uv": [ 3.0, 8.0, 4.4000000059604645, 15.100000031292439 ] },
                "east": { "texture": "#1", "uv": [ 10.0, 1.0, 11.0, 8.100000031292439 ] },
                "south": { "texture": "#1", "uv": [ 13.0, 7.0, 14.400000005960464, 14.100000031292439 ] },
                "west": { "texture": "#1", "uv": [ 9.0, 6.0, 10.0, 13.100000031292439 ] },
                "up": { "texture": "#1", "uv": [ 2.0, 5.0, 3.4000000059604645, 6.0 ] },
                "down": { "texture": "#1", "uv": [ 13.0, 7.0, 14.400000005960464, 8.0 ] }
            }
        },
        {
            "name": "TopBone",
            "from": [ 11.0, 13.0, 7.200000002980232 ], 
            "to": [ 12.100000001490116, 14.0, 8.600000008940697 ], 
            "faces": {
                "north": { "texture": "#1", "uv": [ 0.0, 0.0, 1.1000000014901161, 1.0 ] },
                "east": { "texture": "#1", "uv": [ 0.0, 0.0, 1.4000000059604645, 1.0 ] },
                "south": { "texture": "#1", "uv": [ 0.0, 0.0, 1.1000000014901161, 1.0 ] },
                "west": { "texture": "#1", "uv": [ 0.0, 0.0, 1.4000000059604645, 1.0 ] },
                "up": { "texture": "#1", "uv": [ 0.0, 0.0, 1.1000000014901161, 1.4000000059604645 ] },
                "down": { "texture": "#1", "uv": [ 0.0, 0.0, 1.1000000014901161, 1.4000000059604645 ] }
            }
        },
        {
            "name": "TopBone2",
            "from": [ 10.0, 14.0, 7.200000002980232 ], 
            "to": [ 11.0, 15.0, 8.600000008940697 ], 
            "faces": {
                "north": { "texture": "#1", "uv": [ 0.0, 0.0, 1.0, 1.0 ] },
                "east": { "texture": "#1", "uv": [ 0.0, 0.0, 1.4000000059604645, 1.0 ] },
                "south": { "texture": "#1", "uv": [ 0.0, 0.0, 1.0, 1.0 ] },
                "west": { "texture": "#1", "uv": [ 0.0, 0.0, 1.4000000059604645, 1.0 ] },
                "up": { "texture": "#1", "uv": [ 0.0, 0.0, 1.0, 1.4000000059604645 ] },
                "down": { "texture": "#1", "uv": [ 0.0, 0.0, 1.0, 1.4000000059604645 ] }
            }
        }
    ], 
    
    "display": {
        "thirdperson_righthand": {
            "rotation": [ 0, 90, 0 ],
            "translation": [ 0, 4, 0 ],
            "scale": [ 1.05, 1.05, 1.05 ]
        },
        "thirdperson_lefthand": {
            "rotation": [ 0, -90, 0 ],
            "translation": [ 0, 4, 0 ],
            "scale": [ 1.05, 1.05, 1.05 ]
        },
        "firstperson_righthand": {
            "rotation": [ 0, 90, 0 ],
            "translation": [ -2, -1.5, -8 ],
            "scale": [ 1.4, 1.4, 1.4 ]
        },
        "firstperson_lefthand": {
            "rotation": [ 0, -90, 0 ],
            "translation": [ -2, -1.5, -8 ],
            "scale": [ 1.4, 1.4, 1.4 ]
        },
        "gui": {
            "rotation": [ 0, 0, 0 ],
            "translation": [ 0, 0, 0 ],
            "scale": [ 0.90, 0.90, 0.90 ]
        }
    }

}